django_api_forms/__init__.py
django_api_forms/apps.py
django_api_forms/exceptions.py
django_api_forms/fields.py
django_api_forms/forms.py
django_api_forms/population_strategies.py
django_api_forms/settings.py
django_api_forms/utils.py
django_api_forms/version.py
django_api_forms-0.21.0.dist-info/LICENSE
django_api_forms-0.21.0.dist-info/METADATA
django_api_forms-0.21.0.dist-info/WHEEL
django_api_forms-0.21.0.dist-info/top_level.txt
django_api_forms-0.21.0.dist-info/RECORD
